regml_llmchat_task_helpers/__init__.py
regml_llmchat_task_helpers/helpers/__init__.py
regml_llmchat_task_helpers/helpers/llmchat.py
regml_llmchat_task_helpers/interfaces/__init__.py
regml_llmchat_task_helpers/tests/__init__.py
regml_llmchat_task_helpers/tests/run_llmchat.py
regml_llmchat_task_helpers-0.0.2.dist-info/METADATA
regml_llmchat_task_helpers-0.0.2.dist-info/WHEEL
regml_llmchat_task_helpers-0.0.2.dist-info/RECORD
