Metadata-Version: 2.1
Name: regml_llmchat_task_helpers
Version: 0.0.2
Summary: Regscale ML LLMChat Task Helpers
Author: Luke Bechtel
Author-email: lbechtel@regscale.com
Requires-Python: >=3.8
Classifier: Programming Language :: Python :: 3
Classifier: Programming Language :: Python :: 3.8
Classifier: Programming Language :: Python :: 3.9
Classifier: Programming Language :: Python :: 3.10
Classifier: Programming Language :: Python :: 3.11
Classifier: Programming Language :: Python :: 3.12
Requires-Dist: numpy (>=1.2.3,<2.0.0)
Requires-Dist: regml_core (>=0.0.2,<0.0.3)
Requires-Dist: regml_task_registry_hardcoded (>=0.0.1,<0.0.2)
